boiseopensourcedemo/__init__.py
boiseopensourcedemo/boiseopensourcedemo.py
boiseopensourcedemo-0.0.1.dist-info/DESCRIPTION.rst
boiseopensourcedemo-0.0.1.dist-info/METADATA
boiseopensourcedemo-0.0.1.dist-info/metadata.json
boiseopensourcedemo-0.0.1.dist-info/RECORD
boiseopensourcedemo-0.0.1.dist-info/top_level.txt
boiseopensourcedemo-0.0.1.dist-info/WHEEL
