Metadata-Version: 2.0
Name: boiseopensourcedemo
Version: 0.0.1
Summary: Boise Open Source Demo
Home-page: https://github.com/robustican/boiseopensourcedemo
Author: Jeremy Robin
Author-email: jeremy@talentpair.com
License: BSD
Keywords: boiseopensourcedemo
Platform: UNKNOWN
Classifier: Development Status :: 2 - Pre-Alpha
Classifier: Intended Audience :: Developers
Classifier: License :: OSI Approved :: BSD License
Classifier: Natural Language :: English
Classifier: Programming Language :: Python :: 2
Classifier: Programming Language :: Python :: 2.6
Classifier: Programming Language :: Python :: 2.7
